README.md
setup.py
twaddr/__init__.py
twaddr/addrdata.py
twaddr/county.csv
twaddr/merge.csv
twaddr/roadStreet.csv
twaddr/tran.py
twaddr/village.csv
twaddr.egg-info/PKG-INFO
twaddr.egg-info/SOURCES.txt
twaddr.egg-info/dependency_links.txt
twaddr.egg-info/top_level.txt