Metadata-Version: 1.0
Name: twaddr
Version: 1.0.2
Summary: Taiwan address related services
Home-page: https://github.com/ailan12345/twAddr
Author: Ailan
Author-email: karta2599434@gmail.com
License: UNKNOWN
Keywords: tw,addr
Platform: UNKNOWN
